{
  "page" : {
    "xid" : "page1759",
    "type" : "PuzzleMap",
    "title" : "Puzzle Map",
    "info" : {
      "property" : [ {
        "name" : "puzzlemap",
        "value" : "AFPAKPuzzleMap.json"
      }, {
        "name" : "builtPuzzleMap",
        "value" : "{\n  \"lastModifiedTime\" : 1465851511000,\n  \"pageType\" : \"PuzzleMap\",\n  \"puzzleMapId\" : 20,\n  \"puzzleName\" : \"VCAT AFPAK\",\n  \"dialogX\" : 450,\n  \"dialogY\" : 5,\n  \"lastModifiedBy\" : \"lcorkett\",\n  \"puzzleMapPieces\" : [ {\n    \"name\" : \"Afpak Puzzle Map Test 04\",\n    \"imageFileName\" : \"AFPAK_Puzzle_Map_Test_04.jpg\",\n    \"puzzleMapPieceId\" : 215,\n    \"imageId\" : 976,\n    \"order\" : 0,\n    \"labeledImageId\" : null,\n    \"labeledImageName\" : null,\n    \"correctImageId\" : null,\n    \"correctImageName\" : null,\n    \"offsetX\" : null,\n    \"offsetY\" : null,\n    \"scaleAmount\" : null\n  }, {\n    \"name\" : \"Afghanistan Correct 01\",\n    \"imageFileName\" : \"Afghanistan_Correct_01.png\",\n    \"puzzleMapPieceId\" : 216,\n    \"imageId\" : 977,\n    \"order\" : 1,\n    \"labeledImageId\" : 978,\n    \"labeledImageName\" : \"Afghanistan_Labeled_01.png\",\n    \"correctImageId\" : 979,\n    \"correctImageName\" : \"Afghanistan_Incorrect_01.png\",\n    \"offsetX\" : 408.0,\n    \"offsetY\" : -22.0,\n    \"scaleAmount\" : 0.45\n  }, {\n    \"name\" : \"Iran Correct 01\",\n    \"imageFileName\" : \"Iran_Correct_01.png\",\n    \"puzzleMapPieceId\" : 217,\n    \"imageId\" : 980,\n    \"order\" : 2,\n    \"labeledImageId\" : 981,\n    \"labeledImageName\" : \"Iran_Labeled_01.png\",\n    \"correctImageId\" : 982,\n    \"correctImageName\" : \"Iran_Incorrect_01.png\",\n    \"offsetX\" : 547.0,\n    \"offsetY\" : 22.0,\n    \"scaleAmount\" : 0.3\n  }, {\n    \"name\" : \"Pakistan Correct 01\",\n    \"imageFileName\" : \"Pakistan_Correct_01.png\",\n    \"puzzleMapPieceId\" : 218,\n    \"imageId\" : 983,\n    \"order\" : 3,\n    \"labeledImageId\" : 985,\n    \"labeledImageName\" : \"Pakistan_Labeled_01.png\",\n    \"correctImageId\" : 984,\n    \"correctImageName\" : \"Pakistan_Incorrect_01.png\",\n    \"offsetX\" : 438.0,\n    \"offsetY\" : -8.0,\n    \"scaleAmount\" : 0.35\n  }, {\n    \"name\" : \"Tajikistan Correct 01\",\n    \"imageFileName\" : \"Tajikistan_Correct_01.png\",\n    \"puzzleMapPieceId\" : 219,\n    \"imageId\" : 986,\n    \"order\" : 4,\n    \"labeledImageId\" : 988,\n    \"labeledImageName\" : \"Tajikistan_Labeled_01.png\",\n    \"correctImageId\" : 987,\n    \"correctImageName\" : \"Tajikistan_Incorrect_01.png\",\n    \"offsetX\" : 164.0,\n    \"offsetY\" : -50.0,\n    \"scaleAmount\" : 0.85\n  }, {\n    \"name\" : \"Turkmenistan Correct 01\",\n    \"imageFileName\" : \"Turkmenistan_Correct_01.png\",\n    \"puzzleMapPieceId\" : 220,\n    \"imageId\" : 989,\n    \"order\" : 5,\n    \"labeledImageId\" : 991,\n    \"labeledImageName\" : \"Turkmenistan_Labeled_01.png\",\n    \"correctImageId\" : 990,\n    \"correctImageName\" : \"Turkmenistan_Incorrect_01.png\",\n    \"offsetX\" : 460.0,\n    \"offsetY\" : 19.0,\n    \"scaleAmount\" : 0.5\n  }, {\n    \"name\" : \"Uzbekistan Correct 01\",\n    \"imageFileName\" : \"Uzbekistan_Correct_01.png\",\n    \"puzzleMapPieceId\" : 221,\n    \"imageId\" : 992,\n    \"order\" : 6,\n    \"labeledImageId\" : 994,\n    \"labeledImageName\" : \"Uzbekistan_Labeled_01.png\",\n    \"correctImageId\" : 993,\n    \"correctImageName\" : \"Uzbekistan_Incorrect_01.png\",\n    \"offsetX\" : 424.0,\n    \"offsetY\" : 50.0,\n    \"scaleAmount\" : 0.5\n  } ]\n}"
      } ]
    }
  }
}