{
  "page" : {
    "xid" : "page3942",
    "type" : "Info",
    "title" : "Introductory Remarks",
    "comment" : "",
    "info" : {
      "property" : [ {
        "name" : "mediacaption",
        "value" : "https://www.flickr.com/photos/dvids/5661625753/"
      }, {
        "name" : "mediadisplayblurb",
        "value" : "A young girl in central Afghanistan"
      } ]
    },
    "skills" : null,
    "note" : [ {
      "text" : "Afghanistan is a rugged and beautiful country with untapped natural reserves of gemstones and minerals. While the Afghan people are ethnically and linguistically diverse, they share the common values of honor and hospitality. Although war has taken a toll on the country, Afghanistan is rebuilding its infrastructure and healing its divisions.",
      "media" : [ {
        "zid" : 4032322,
        "xid" : "4032322.mp3",
        "type" : "audio",
        "file" : "4032322.mp3"
      } ]
    } ],
    "media" : [ {
      "zid" : 1457469101200,
      "xid" : "1457469101200.jpg",
      "type" : "image",
      "file" : "1457469101200.jpg",
      "mime" : "image/jpeg",
      "info" : {
        "property" : [ {
          "name" : "imagination",
          "value" : ""
        } ]
      }
    } ]
  }
}