{
  "page" : {
    "xid" : "page3803",
    "type" : "Info",
    "title" : "Types of Interpretation",
    "info" : {
      "property" : [ {
        "name" : "mediacaption",
        "value" : "https://www.flickr.com/photos/itupictures/8207252733/"
      }, {
        "name" : "mediadisplayblurb",
        "value" : "Simultaneous interpretation booths at a conference in Dubai, UAE"
      } ]
    },
    "note" : [ {
      "text" : "There are three chief types of interpretation. \"Simultaneous interpretation\" refers to a situation where a communication is interpreted at the same time as it is spoken. ",
      "media" : [ {
        "zid" : 4022077,
        "xid" : "4022077.mp3",
        "type" : "audio",
        "file" : "4022077.mp3"
      } ]
    }, {
      "text" : "In \"consecutive interpretation,\" a speaker pauses at long regular intervals to allow the message to be interpreted. ",
      "media" : [ {
        "zid" : 4022078,
        "xid" : "4022078.mp3",
        "type" : "audio",
        "file" : "4022078.mp3"
      } ]
    }, {
      "text" : "\"Escort interpretation,\" which is a form of consecutive interpretation, refers to the two-way interpretation of conversations between two or more individuals. Speakers pause frequently to allow the interpreter to repeat what has just been said. The defining trait of escort interpretation is its two-way nature.",
      "media" : [ {
        "zid" : 4022079,
        "xid" : "4022079.mp3",
        "type" : "audio",
        "file" : "4022079.mp3"
      } ]
    } ],
    "media" : [ {
      "zid" : 1416959420010,
      "xid" : "1416959420010.jpg",
      "type" : "image",
      "file" : "1416959420010.jpg",
      "mime" : "image/jpeg",
      "info" : {
        "property" : [ {
          "name" : "mediacaption",
          "value" : "NASA's Earth Observatory"
        }, {
          "name" : "mediadisplayblurb",
          "value" : "Map of Afghanistan"
        } ]
      }
    } ]
  }
}